README
setup.cfg
setup.py
test/test_hooks.py
test/test_initialization.py
test/test_twanager_command.py
test/test_web.py
tiddlywebplugins/__init__.py
tiddlywebplugins.tagdex.egg-info/PKG-INFO
tiddlywebplugins.tagdex.egg-info/SOURCES.txt
tiddlywebplugins.tagdex.egg-info/dependency_links.txt
tiddlywebplugins.tagdex.egg-info/namespace_packages.txt
tiddlywebplugins.tagdex.egg-info/not-zip-safe
tiddlywebplugins.tagdex.egg-info/requires.txt
tiddlywebplugins.tagdex.egg-info/top_level.txt
tiddlywebplugins/tagdex/__init__.py
tiddlywebplugins/tagdex/commands.py
tiddlywebplugins/tagdex/database.py
tiddlywebplugins/tagdex/hooks.py
tiddlywebplugins/tagdex/web.py