Metadata-Version: 1.0
Name: tiddlywebplugins.tagdex
Version: 0.5.3
Summary: TiddlyWeb indexer for faceted tag-based tiddler retrieval
Home-page: https://github.com/FND/tiddlywebplugins.tagdex
Author: FND
Author-email: UNKNOWN
License: BSD
Platform: Posix; MacOS X; Windows
